addition_module/__init__.py
addition_module/obfuscated/addition.py
addition_module/obfuscated/__pycache__/addition.cpython-310.pyc
addition_module/obfuscated/pyarmor_runtime_000000/__init__.py
addition_module/obfuscated/pyarmor_runtime_000000/pyarmor_runtime.so
addition_module/obfuscated/pyarmor_runtime_000000/__pycache__/__init__.cpython-310.pyc
addition_module-0.1.1.dist-info/licenses/LICENSE
addition_module-0.1.1.dist-info/METADATA
addition_module-0.1.1.dist-info/WHEEL
addition_module-0.1.1.dist-info/top_level.txt
addition_module-0.1.1.dist-info/RECORD
